divide/__init__.py
divide/divide_by_three.py
multiply/__init__.py
multiply/multiply_by_three.py
mibellisvetlana_package_name-0.15.12.dist-info/LICENSE.txt
mibellisvetlana_package_name-0.15.12.dist-info/METADATA
mibellisvetlana_package_name-0.15.12.dist-info/WHEEL
mibellisvetlana_package_name-0.15.12.dist-info/top_level.txt
mibellisvetlana_package_name-0.15.12.dist-info/RECORD
