Metadata-Version: 2.1
Name: mibellisvetlana-package-name
Version: 0.15.12
Summary: A simple Python package
Author: Svetlana Luneva
Author-email: mibellisvetlana@gmail.com
Classifier: Programming Language :: Python :: 3
Classifier: License :: OSI Approved :: MIT License
Classifier: Operating System :: OS Independent
Requires-Python: >=3.6
License-File: LICENSE.txt
